vkteams/__init__.py
vkteams/bot.py
vkteams/constant.py
vkteams/dispatcher.py
vkteams/event.py
vkteams/filter.py
vkteams/handler.py
vkteams/myteam.py
vkteams/types.py
vkteams/util.py
vkteams-0.0.3.dist-info/LICENSE
vkteams-0.0.3.dist-info/METADATA
vkteams-0.0.3.dist-info/WHEEL
vkteams-0.0.3.dist-info/top_level.txt
vkteams-0.0.3.dist-info/RECORD
