Metadata-Version: 2.1
Name: vkteams
Version: 0.0.3
Summary: Pure Python interface for Bot API. Bot cookbook for Humans.
Home-page: https://github.com/alex3ysmirnov/vkteams
Author: alex3ysmirnov
Author-email: alex3ysmirnov@gmail.com
License: MIT
Keywords: mailru im bot api postmaster alex3ysmirnov vkteams vk teams
Platform: UNKNOWN
Classifier: Intended Audience :: Developers
Classifier: Topic :: Software Development :: Libraries :: Python Modules
Classifier: Topic :: Communications :: Chat
Classifier: Topic :: Internet
Classifier: Programming Language :: Python :: 2
Classifier: Programming Language :: Python :: 2.7
Classifier: Programming Language :: Python :: 3
Classifier: Programming Language :: Python :: 3.4
Classifier: Programming Language :: Python :: 3.5
Classifier: Programming Language :: Python :: 3.6
Classifier: Programming Language :: Python :: 3.7
Classifier: Programming Language :: Python :: 3.8
Classifier: Programming Language :: Python :: 3.9
Classifier: Programming Language :: Python :: 3.10
Classifier: Operating System :: OS Independent
Requires-Python: >= 2.7, != 3.0.*, != 3.1.*, != 3.2.*, != 3.3.*
License-File: LICENSE
Requires-Dist: cached-property==1.5.2
Requires-Dist: expiringdict==1.2.1
Requires-Dist: monotonic==1.6
Requires-Dist: python-baseconv==1.2.2
Requires-Dist: requests==2.31.0
Requires-Dist: six==1.16.0
Requires-Dist: gTTS==2.2.3
Requires-Dist: urllib3==1.26.18
Requires-Dist: click>=8.0.3
Requires-Dist: enum34==1.1.6; python_version < "3.4"
